MANIFEST.in
README.rst
setup.cfg
setup.py
cs/__init__.py
cs.pfg.multifile.egg-info/PKG-INFO
cs.pfg.multifile.egg-info/SOURCES.txt
cs.pfg.multifile.egg-info/dependency_links.txt
cs.pfg.multifile.egg-info/entry_points.txt
cs.pfg.multifile.egg-info/namespace_packages.txt
cs.pfg.multifile.egg-info/not-zip-safe
cs.pfg.multifile.egg-info/requires.txt
cs.pfg.multifile.egg-info/top_level.txt
cs/pfg/__init__.py
cs/pfg/multifile/README.txt
cs/pfg/multifile/__init__.py
cs/pfg/multifile/config.py
cs/pfg/multifile/configure.zcml
cs/pfg/multifile/tests.py
cs/pfg/multifile/version.txt
cs/pfg/multifile/browser/__init__.py
cs/pfg/multifile/browser/configure.zcml
cs/pfg/multifile/browser/jquery.filer/assets/fonts/jquery.filer-icons/jquery-filer-preview.html
cs/pfg/multifile/browser/jquery.filer/assets/fonts/jquery.filer-icons/jquery-filer.css
cs/pfg/multifile/browser/jquery.filer/assets/fonts/jquery.filer-icons/jquery-filer.eot
cs/pfg/multifile/browser/jquery.filer/assets/fonts/jquery.filer-icons/jquery-filer.svg
cs/pfg/multifile/browser/jquery.filer/assets/fonts/jquery.filer-icons/jquery-filer.ttf
cs/pfg/multifile/browser/jquery.filer/assets/fonts/jquery.filer-icons/jquery-filer.woff
cs/pfg/multifile/browser/jquery.filer/css/jquery.filer.css
cs/pfg/multifile/browser/jquery.filer/css/themes/jquery.filer-dragdropbox-theme.css
cs/pfg/multifile/browser/jquery.filer/js/custom.js
cs/pfg/multifile/browser/jquery.filer/js/jquery.filer.js
cs/pfg/multifile/browser/jquery.filer/js/jquery.filer.min.js
cs/pfg/multifile/content/__init__.py
cs/pfg/multifile/content/configure.zcml
cs/pfg/multifile/content/formmultifilefield.py
cs/pfg/multifile/content/widgets.py
cs/pfg/multifile/interfaces/__init__.py
cs/pfg/multifile/interfaces/formmultifilefield.py
cs/pfg/multifile/profiles/default/factorytool.xml
cs/pfg/multifile/profiles/default/metadata.xml
cs/pfg/multifile/profiles/default/rolemap.xml
cs/pfg/multifile/profiles/default/skins.xml
cs/pfg/multifile/profiles/default/types.xml
cs/pfg/multifile/profiles/default/workflows.xml
cs/pfg/multifile/profiles/default/types/FormFolder.xml
cs/pfg/multifile/profiles/default/types/FormMultiFileField.xml
cs/pfg/multifile/skins/multifile_skins/upload_widget.pt
cs/pfg/multifile/tests/__init__.py
cs/pfg/multifile/tests/base.py
cs/pfg/multifile/tests/test_doctest.py
docs/HISTORY.txt
