Metadata-Version: 1.1
Name: cs.pfg.multifile
Version: 1.0.1
Summary: PloneFormGen fields to allow uploading multiple files
Home-page: https://github.com/codesyntax/cs.pfg.multifile
Author: Mikel Larreategi
Author-email: mlarreategi@codesyntax.com
License: GPL
Platform: UNKNOWN
Classifier: Framework :: Plone
Classifier: Programming Language :: Python
